{
  "users": [
    {
      "id": "93c01fcd-e3a1-45d7-9911-c7ce3f7b219a",
      "email": "kaseddie@gmail.com",
      "workosUserId": "user_01KAG6C4A4TKANKBDN23TMCD11",
      "kycStatus": "verified",
      "walletBalance": 19299.100000000013,
      "activeStrategy": null,
      "stripeCustomerId": null,
      "createdAt": "2025-11-22T11:59:15.478Z",
      "updatedAt": "2025-11-24T14:43:23.720Z",
      "kycVerifiedAt": "2025-11-22T18:51:35.402Z",
      "kycDocuments": {
        "idDocument": "National ID.jpg",
        "selfie": "First KYC Test Phot.jpg"
      }
    }
  ],
  "trades": [
    {
      "id": "21f64385-eba5-4a2e-bf69-8725c864382e",
      "userId": "93c01fcd-e3a1-45d7-9911-c7ce3f7b219a",
      "symbol": "BTC",
      "strategy": "momentum",
      "action": "BUY",
      "price": 85799.99,
      "amount": 0.001165501301340478,
      "usdValue": 100,
      "fee": 0.1,
      "stopLoss": 84083.9902,
      "takeProfit": 89231.98960000002,
      "confidence": 83,
      "reasoning": "Strong upward momentum with healthy RSI",
      "status": "completed",
      "timestamp": "2025-11-23T07:51:05.850Z"
    },
    {
      "id": "58d5547d-d3e4-4612-be83-5c9f3f349f9f",
      "userId": "93c01fcd-e3a1-45d7-9911-c7ce3f7b219a",
      "symbol": "BTC",
      "strategy": "momentum",
      "action": "BUY",
      "price": 86049.02,
      "amount": 0.0011621282845522237,
      "usdValue": 100,
      "fee": 0.1,
      "stopLoss": 84328.0396,
      "takeProfit": 89490.9808,
      "confidence": 82,
      "reasoning": "Strong upward momentum with healthy RSI",
      "status": "completed",
      "timestamp": "2025-11-23T08:50:22.160Z"
    },
    {
      "id": "c60f5442-e80e-473b-aaca-9d221eea437a",
      "userId": "93c01fcd-e3a1-45d7-9911-c7ce3f7b219a",
      "symbol": "BTC",
      "strategy": "momentum",
      "action": "BUY",
      "price": 86107.56,
      "amount": 0.0011613382146701172,
      "usdValue": 100,
      "fee": 0.1,
      "stopLoss": 84385.40879999999,
      "takeProfit": 89551.8624,
      "confidence": 87,
      "reasoning": "Strong upward momentum with healthy RSI",
      "status": "completed",
      "timestamp": "2025-11-23T08:56:47.830Z"
    },
    {
      "id": "c1bba418-1fe8-4e1f-ac7d-004a4e6026df",
      "userId": "93c01fcd-e3a1-45d7-9911-c7ce3f7b219a",
      "symbol": "BTC",
      "strategy": "mean-reversion",
      "action": "BUY",
      "price": 86129.27,
      "amount": 0.0011610454843051612,
      "usdValue": 100,
      "fee": 0.1,
      "stopLoss": 84406.68460000001,
      "takeProfit": 89574.44080000001,
      "confidence": 70,
      "reasoning": "Price near fair value, accumulating",
      "status": "completed",
      "timestamp": "2025-11-23T08:57:28.346Z"
    },
    {
      "id": "037cee52-59d3-4dcb-a844-5c8bbc609706",
      "userId": "93c01fcd-e3a1-45d7-9911-c7ce3f7b219a",
      "symbol": "BTC",
      "strategy": "momentum",
      "action": "BUY",
      "price": 91250,
      "amount": 0.001095890410958904,
      "usdValue": 100,
      "fee": 0.1,
      "stopLoss": 89425,
      "takeProfit": 94900,
      "confidence": 89,
      "reasoning": "Strong upward momentum with healthy RSI",
      "status": "completed",
      "timestamp": "2025-11-24T08:02:59.272Z"
    },
    {
      "id": "5a4c3a0c-ce9b-4a22-a4a9-0788a90d8a7d",
      "userId": "93c01fcd-e3a1-45d7-9911-c7ce3f7b219a",
      "symbol": "BTC",
      "strategy": "trend-following",
      "action": "BUY",
      "price": 91250,
      "amount": 0.001095890410958904,
      "usdValue": 100,
      "fee": 0.1,
      "stopLoss": 89425,
      "takeProfit": 94900,
      "confidence": 88,
      "reasoning": "Strong momentum detected based on recent high trading volume and positive regulatory news.",
      "status": "completed",
      "timestamp": "2025-11-24T08:14:08.395Z"
    },
    {
      "id": "290b07fb-fb2b-4a8e-ad05-02c65c6a6b6e",
      "userId": "93c01fcd-e3a1-45d7-9911-c7ce3f7b219a",
      "symbol": "BTC",
      "strategy": "volume-spike",
      "action": "BUY",
      "price": 91250,
      "amount": 0.001095890410958904,
      "usdValue": 100,
      "fee": 0.1,
      "stopLoss": 89425,
      "takeProfit": 94900,
      "confidence": 91,
      "reasoning": "Massive volume spike with price increase",
      "status": "completed",
      "timestamp": "2025-11-24T08:14:59.561Z"
    },
    {
      "id": "6259ae97-83a9-4da9-b1dc-2941f3d20afb",
      "userId": "93c01fcd-e3a1-45d7-9911-c7ce3f7b219a",
      "symbol": "BTC",
      "strategy": "support-resistance",
      "action": "SELL",
      "price": 91250,
      "amount": 0.001095890410958904,
      "usdValue": 100,
      "fee": 0.1,
      "stopLoss": 93075,
      "takeProfit": 87600,
      "confidence": 77,
      "reasoning": "Price near resistance level",
      "status": "completed",
      "timestamp": "2025-11-24T08:15:05.722Z"
    },
    {
      "id": "151e48ae-91d3-4cfa-a3fc-3eca894ee43a",
      "userId": "93c01fcd-e3a1-45d7-9911-c7ce3f7b219a",
      "symbol": "BTC",
      "strategy": "momentum",
      "action": "BUY",
      "price": 85779.66,
      "amount": 0.0011657775281459497,
      "usdValue": 100,
      "fee": 0.1,
      "stopLoss": 84064.0668,
      "takeProfit": 89210.84640000001,
      "confidence": 79,
      "reasoning": "Momentum building, good entry point",
      "status": "completed",
      "timestamp": "2025-11-24T14:43:24.202Z"
    }
  ]
}